{
  "difficulty": "hard",
  "grid": [
    [
      {"terrain": "water", "object": "none"},
      {"terrain": "mud", "object": "rock"},
      {"terrain": "water", "object": "none"}
    ],
    [
      {"terrain": "grass", "object": "none"},
      {"terrain": "sand", "object": "none"},
      {"terrain": "mud", "object": "tree"}
    ],
    [
      {"terrain": "grass", "object": "none"},
      {"terrain": "mud", "object": "none"},
      {"terrain": "mud", "object": "none"}
    ]
  ],
  "animals": [
    "fox",
    "monkey",
    "frog",
    "rabbit",
    "elephant"
  ],
  "clues": [
    {
      "id": 1,
      "description": "Rabbit is on GRASS",
      "complexity": 1
    },
    {
      "id": 2,
      "description": "Frog is NOT adjacent to Fox",
      "complexity": 3
    },
    {
      "id": 3,
      "description": "Frog is in the same row as a ROCK",
      "complexity": 3
    },
    {
      "id": 4,
      "description": "Elephant is adjacent to Fox",
      "complexity": 4
    },
    {
      "id": 5,
      "description": "Rabbit is in Row 3 OR Row 1",
      "complexity": 4
    },
    {
      "id": 6,
      "description": "Frog is adjacent to Monkey",
      "complexity": 4
    },
    {
      "id": 7,
      "description": "Monkey is in Row 1",
      "complexity": 2
    },
    {
      "id": 8,
      "description": "Monkey is adjacent to Elephant",
      "complexity": 4
    },
    {
      "id": 9,
      "description": "Monkey is in Column C",
      "complexity": 2
    }
  ],
  "solution": {
    "frog": {"row": 1, "column": "B"},
    "monkey": {"row": 1, "column": "C"},
    "elephant": {"row": 2, "column": "C"},
    "rabbit": {"row": 3, "column": "A"},
    "fox": {"row": 3, "column": "C"}
  }
}

