{
  "difficulty": "CUSTOM",
  "negative_only": false,
  "grid_size": 3,
  "clue_count": 10,
  "solution": [
    [{"color": "GREEN", "shape": "CIRCLE"}, {"color": "RED", "shape": "TRIANGLE"}, {"color": "RED", "shape": "CIRCLE"}],
    [{"color": "BLUE", "shape": "CIRCLE"}, {"color": "GREEN", "shape": "TRIANGLE"}, {"color": "RED", "shape": "SQUARE"}],
    [{"color": "BLUE", "shape": "SQUARE"}, {"color": "GREEN", "shape": "SQUARE"}, {"color": "BLUE", "shape": "TRIANGLE"}]
  ],
  "clues": [
    {"type": "DIAGONAL_PAIR", "negative": false, "direction": "ANTI_AXIS", "top": {"color": "GREEN", "shape": null}, "bottom": {"color": null, "shape": "SQUARE"}},
    {"type": "SINGLE_POINT", "negative": false, "row": 2, "col": 1, "pattern": {"color": "GREEN", "shape": null}},
    {"type": "FLOATING_LINE", "negative": false, "is_row": false, "patterns": [{"color": null, "shape": "CIRCLE"}, {"color": null, "shape": null}, {"color": "BLUE", "shape": null}]},
    {"type": "FLOATING_LINE", "negative": false, "is_row": true, "patterns": [{"color": null, "shape": "SQUARE"}, {"color": null, "shape": null}, {"color": "BLUE", "shape": null}]},
    {"type": "RELATIVE_SHAPE", "negative": false, "shape_name": "CHAIN", "parts": [{"dr": 0, "dc": 0, "pattern": {"color": null, "shape": "TRIANGLE"}}, {"dr": 0, "dc": 1, "pattern": {"color": "RED", "shape": "SQUARE"}}, {"dr": -1, "dc": 1, "pattern": {"color": "RED", "shape": null}}]},
    {"type": "SINGLE_POINT", "negative": true, "row": 2, "col": 1, "pattern": {"color": null, "shape": "CIRCLE"}},
    {"type": "DIAGONAL_PAIR", "negative": true, "direction": "MAIN_AXIS", "top": {"color": null, "shape": "CIRCLE"}, "bottom": {"color": "RED", "shape": "SQUARE"}},
    {"type": "DIAGONAL_PAIR", "negative": true, "direction": "MAIN_AXIS", "top": {"color": null, "shape": "TRIANGLE"}, "bottom": {"color": "GREEN", "shape": null}},
    {"type": "RELATIVE_SHAPE", "negative": true, "shape_name": "CHAIN", "parts": [{"dr": 0, "dc": 0, "pattern": {"color": "GREEN", "shape": null}}, {"dr": 0, "dc": 1, "pattern": {"color": null, "shape": "CIRCLE"}}, {"dr": -1, "dc": 1, "pattern": {"color": null, "shape": "SQUARE"}}]},
    {"type": "SINGLE_POINT", "negative": true, "row": 1, "col": 0, "pattern": {"color": "GREEN", "shape": "CIRCLE"}}
  ]
}
