{
  "difficulty": "CUSTOM",
  "negative_only": false,
  "grid_size": 3,
  "clue_count": 8,
  "solution": [
    [{"color": "BLUE", "shape": "CIRCLE"}, {"color": "RED", "shape": "SQUARE"}, {"color": "GREEN", "shape": "SQUARE"}],
    [{"color": "RED", "shape": "TRIANGLE"}, {"color": "RED", "shape": "CIRCLE"}, {"color": "BLUE", "shape": "SQUARE"}],
    [{"color": "GREEN", "shape": "TRIANGLE"}, {"color": "BLUE", "shape": "TRIANGLE"}, {"color": "GREEN", "shape": "CIRCLE"}]
  ],
  "clues": [
    {"type": "DIAGONAL_PAIR", "negative": false, "direction": "MAIN_AXIS", "top": {"color": null, "shape": "SQUARE"}, "bottom": {"color": "BLUE", "shape": null}},
    {"type": "SINGLE_POINT", "negative": false, "row": 2, "col": 2, "pattern": {"color": null, "shape": "CIRCLE"}},
    {"type": "FLOATING_LINE", "negative": false, "is_row": true, "patterns": [{"color": null, "shape": null}, {"color": null, "shape": "SQUARE"}, {"color": null, "shape": null}]},
    {"type": "FLOATING_LINE", "negative": false, "is_row": false, "patterns": [{"color": null, "shape": "CIRCLE"}, {"color": "RED", "shape": null}, {"color": "GREEN", "shape": null}]},
    {"type": "MULTI_POINT", "negative": false, "constraints": [{"type": "SINGLE_POINT", "negative": false, "row": 2, "col": 0, "pattern": {"color": "GREEN", "shape": null}}, {"type": "SINGLE_POINT", "negative": false, "row": 1, "col": 2, "pattern": {"color": null, "shape": "SQUARE"}}]},
    {"type": "SINGLE_POINT", "negative": false, "row": 0, "col": 2, "pattern": {"color": "GREEN", "shape": "SQUARE"}},
    {"type": "DIAGONAL_PAIR", "negative": false, "direction": "ANTI_AXIS", "top": {"color": "GREEN", "shape": null}, "bottom": {"color": "RED", "shape": "CIRCLE"}},
    {"type": "DIAGONAL_PAIR", "negative": true, "direction": "MAIN_AXIS", "top": {"color": "RED", "shape": null}, "bottom": {"color": "BLUE", "shape": "CIRCLE"}}
  ]
}
